{
    "id": "HV11-009",
    "name": "Yamaguchi Tadashi",
    "rarity": "R",
    "stats": {
        "serve": 2,
        "receive": 4,
        "toss": 0,
        "attack": 0,
        "block": 0
    },
    "skill": {
        "description": "Khi thẻ này xuất hiện ở khu vực Giao Bóng, ở lượt tiếp theo của đối phương, đối phương không được phép đưa ra nhân vật lớp 9 hoặc lớp 12 ở khu vực Đập Bóng."
    },
    "school": "Karasuno",
    "artwork": "Card/Karasuno/Nhan vat/yamaguchi-tadashi-4.png",
    "class": 10,
    "position": "Chặn Giữa"
}
